srtConvert.py
srt/__init__.py
srt/srt2shp.py
srt2shp-0.0.1.dist-info/METADATA
srt2shp-0.0.1.dist-info/WHEEL
srt2shp-0.0.1.dist-info/licenses/LICENSE
srt2shp-0.0.1.dist-info/RECORD
