Metadata-Version: 2.1
Name: srt2shp
Version: 0.0.1
Summary: Parses SRT files produced by DJI drones when recording video.  Converts data into an excel spreadsheet and ESRI shapefiles (Points and Lines).
Project-URL: homepage, https://github.com/ecallahan573/srt2shp
Project-URL: documentation, https://github.com/ecallahan573/srt2shp
Project-URL: repository, https://github.com/ecallahan573/srt2shp
Author: Eric Callahan
License: GNU GENERAL PUBLIC LICENSE
License-File: LICENSE
Classifier: Development Status :: 4 - Beta
Classifier: License :: OSI Approved :: GNU General Public License v3 (GPLv3)
Classifier: Natural Language :: English
Classifier: Operating System :: OS Independent
Classifier: Programming Language :: Python :: 3.9
Classifier: Topic :: Scientific/Engineering :: GIS
Requires-Python: >=3.9
Requires-Dist: openpyxl==3.0.10
Requires-Dist: pandas==1.4.3
Requires-Dist: pyshp==2.1.3
